lethai/__init__.py
lethai/nlg.py
lethai/public/nlg.html
lethai/public/nlg.js
lethai/public/nlg_json.js
lethai/public/styles.css
lethai/utils/__init__.py
lethai-0.0.7.dist-info/WHEEL
lethai-0.0.7.dist-info/METADATA
lethai-0.0.7.dist-info/RECORD
