Metadata-Version: 2.1
Name: lethai
Version: 0.0.7
Summary: Lethical AI python library
License: MIT
Author: Amanl04
Author-email: amanlodha423@outlook.com
Requires-Python: >=3.6.2,<4.0.0
Classifier: License :: OSI Approved :: MIT License
Classifier: Programming Language :: Python :: 3
Classifier: Programming Language :: Python :: 3.7
Classifier: Programming Language :: Python :: 3.8
Requires-Dist: numpy (>=1.19.4,<2.0.0)
Requires-Dist: requests (>=2.25.0,<3.0.0)
Requires-Dist: transformers (>=4.0.1,<5.0.0)
